<?xml version="1.0" encoding="utf-8"?>
<savedqueries xmlns:xsi="http://www.w3.org/2001/XMLSchema-instance">
  <savedquery>
    <IsCustomizable>1</IsCustomizable>
    <CanBeDeleted>0</CanBeDeleted>
    <isquickfindquery>0</isquickfindquery>
    <isprivate>0</isprivate>
    <isdefault>1</isdefault>
    <savedqueryid>{cfb9004a-ada9-426b-8781-f4b509123120}</savedqueryid>
    <layoutxml>
      <grid name="resultset" jump="mshied_name" select="1" icon="1" preview="1">
        <row name="result" id="mshied_studentassessmentitemresponseid">
          <cell name="mshied_name" width="300" />
          <cell name="mshied_assessmentdeliveryid" width="100" />
          <cell name="mshied_assessmentitemid" width="100" />
          <cell name="mshied_assessmentitemscore" width="100" />
          <cell name="mshied_studentid" width="100" />
          <cell name="mshied_studentresponse" width="100" disableSorting="1" />
        </row>
      </grid>
    </layoutxml>
    <querytype>0</querytype>
    <fetchxml>
      <fetch version="1.0" mapping="logical">
        <entity name="mshied_studentassessmentitemresponse">
          <attribute name="mshied_name" />
          <order attribute="mshied_name" descending="false" />
          <filter type="and">
            <condition attribute="statecode" operator="eq" value="0" />
          </filter>
          <attribute name="mshied_studentresponse" />
          <attribute name="mshied_studentid" />
          <attribute name="mshied_assessmentitemscore" />
          <attribute name="mshied_assessmentitemid" />
          <attribute name="mshied_assessmentdeliveryid" />
          <attribute name="mshied_studentassessmentitemresponseid" />
        </entity>
      </fetch>
    </fetchxml>
    <IntroducedVersion>1.0.0.0</IntroducedVersion>
    <LocalizedNames>
      <LocalizedName description="Active Student Assessment Item Responses" languagecode="1033" />
    </LocalizedNames>
  </savedquery>
</savedqueries>