<?xml version="1.0" encoding="utf-8"?>
<AppModuleSiteMap xmlns:xsi="http://www.w3.org/2001/XMLSchema-instance">
  <SiteMapUniqueName>mshied_HigherEd</SiteMapUniqueName>
  <SiteMap>
    <Area Id="NewArea_aa439169" ResourceId="SitemapDesigner.NewArea" VectorIcon="$webresource:mshied_HigherEdIconforUI2" Icon="/WebResources/msdyn_/Images/Area_Default_Icon.png" ShowGroups="false" ordinalvalue="0">
      <Group Id="NewGroup_972e538b" ResourceId="SitemapDesigner.NewGroup" IsProfile="false" ToolTipResourseId="SitemapDesigner.Unknown" ordinalvalue="1">
        <SubArea Id="NewSubArea_5d1bd007" Icon="/_imgs/imagestrips/transparent_spacer.gif" Entity="mshied_extracurricularactivities" Client="All,Outlook,OutlookLaptopClient,OutlookWorkstationClient,Web" AvailableOffline="true" PassParams="false" Sku="All,OnPremise,Live,SPLA" ordinalvalue="3" solutionaction="Modified" />
        <SubArea Id="NewSubArea_f211b1bd" Icon="/_imgs/imagestrips/transparent_spacer.gif" Entity="mshied_areaofinterest" Client="All,Outlook,OutlookLaptopClient,OutlookWorkstationClient,Web" AvailableOffline="true" PassParams="false" Sku="All,OnPremise,Live,SPLA" ordinalvalue="4" solutionaction="Modified" />
        <SubArea Id="NewSubArea_55f9ed49" Icon="/_imgs/imagestrips/transparent_spacer.gif" Entity="mshied_areaofstudy" Client="All,Outlook,OutlookLaptopClient,OutlookWorkstationClient,Web" AvailableOffline="true" PassParams="false" Sku="All,OnPremise,Live,SPLA" ordinalvalue="5" solutionaction="Modified" />
        <SubArea Id="NewSubArea_d3b4c423" Icon="/_imgs/imagestrips/transparent_spacer.gif" Entity="mshied_programrequirement" Client="All,Outlook,OutlookLaptopClient,OutlookWorkstationClient,Web" AvailableOffline="true" PassParams="false" Sku="All,OnPremise,Live,SPLA" ordinalvalue="2" solutionaction="Added" />
      </Group>
      <Group Id="NewGroup_8518009f" ResourceId="SitemapDesigner.NewGroup" IsProfile="false" ToolTipResourseId="SitemapDesigner.Unknown" ordinalvalue="2">
        <SubArea Id="NewSubArea_49c16ffe" Icon="/_imgs/imagestrips/transparent_spacer.gif" Entity="mshied_grant" Client="All,Outlook,OutlookLaptopClient,OutlookWorkstationClient,Web" AvailableOffline="true" PassParams="false" Sku="All,OnPremise,Live,SPLA" ordinalvalue="2" solutionaction="Added">
          <Titles>
            <Title LCID="1033" Title="Grants" ordinalvalue="0" />
          </Titles>
        </SubArea>
        <SubArea Id="NewSubArea_c536ac48" Icon="/_imgs/imagestrips/transparent_spacer.gif" Entity="mshied_studentresource" Client="All,Outlook,OutlookLaptopClient,OutlookWorkstationClient,Web" AvailableOffline="true" PassParams="false" Sku="All,OnPremise,Live,SPLA" ordinalvalue="3" solutionaction="Added" />
      </Group>
    </Area>
  </SiteMap>
  <LocalizedNames>
    <LocalizedName description="Higher Ed" languagecode="1033" />
  </LocalizedNames>
</AppModuleSiteMap>